{
  "location": "پارس آباد",
  "date": "۱۴۰۵/۴/۱۶",
  "time": "۱۶:۴۰",
  "temp": 29,
  "feelsLike": 29,
  "icon": "⛅",
  "desc": "نیمه ابری",
  "forecast": "پیام سیستم: این بخش بزودی بروزرسانی میشود ⚠️",
  "details": [
    { "name": "🌬 سرعت باد", "value": "۱۴ km/h" },
    { "name": "💧 رطوبت", "value": "۴۱٪" },
    { "name": "👁 دید", "value": "۲۴ km" },
    { "name": "📊 فشار", "value": "۱۰۱۰ hPa" },
    { "name": "🌅 طلوع", "value": "۰۴:۵۸" },
    { "name": "🌇 غروب", "value": "۱۹:۴۹" },
    { "name": "☁️ پوشش ابر", "value": "۹۷٪" },
    { "name": "🌫 آلودگی هوا", "value": "🟢 خوب" }
  ]
}
